hiperwalk/__init__.py
hiperwalk/_constants.py
hiperwalk/graph/__init__.py
hiperwalk/graph/_sym_dir_multigraph.py
hiperwalk/graph/complete.py
hiperwalk/graph/complete_bipartite.py
hiperwalk/graph/cycle.py
hiperwalk/graph/graph.py
hiperwalk/graph/grid.py
hiperwalk/graph/hypercube.py
hiperwalk/graph/integer_lattice.py
hiperwalk/graph/line.py
hiperwalk/graph/multigraph.py
hiperwalk/graph/weighted_graph.py
hiperwalk/plot/__init__.py
hiperwalk/plot/_plot.py
hiperwalk/quantum_walk/__init__.py
hiperwalk/quantum_walk/_pyneblina_interface.py
hiperwalk/quantum_walk/coined.py
hiperwalk/quantum_walk/continuous_time.py
hiperwalk/quantum_walk/quantum_walk.py
hiperwalk-2.0b18.dist-info/METADATA
hiperwalk-2.0b18.dist-info/WHEEL
hiperwalk-2.0b18.dist-info/licenses/LICENSE
hiperwalk-2.0b18.dist-info/RECORD
