Metadata-Version: 2.3
Name: hiperwalk
Version: 2.0b18
Summary: High-Performance Quantum Walk Simulator
Project-URL: homepage, http://qubit.lncc.br/qwalk/
Project-URL: documentation, https://hiperwalk.readthedocs.io/
Project-URL: source, https://github.com/hiperwalk/hiperwalk
Author-email: Gustavo Bezerra <gbezerra@posgrad.lncc.br>, Paulo Motta <prmottajr@gmail.com>, Renato Portugal <portugal@lncc.br>
Maintainer-email: Hiperwalk Organization <hiperwalk@gmail.com>
License: GNU Lesser General Public License
License-File: LICENSE
Classifier: License :: OSI Approved :: GNU Lesser General Public License v3 (LGPLv3)
Classifier: Operating System :: POSIX :: Linux
Classifier: Programming Language :: Python :: 3
Classifier: Programming Language :: Python :: 3.8
Requires-Python: >=3.7
Requires-Dist: matplotlib>=3.7
Requires-Dist: networkx>=3.1
Requires-Dist: numpy>=1.24
Requires-Dist: scipy>=1.10
Provides-Extra: doc
Requires-Dist: numpydoc>=1.2; extra == 'doc'
Requires-Dist: pydata-sphinx-theme>=0.11; extra == 'doc'
Requires-Dist: sphinx-autodoc-typehints; extra == 'doc'
Requires-Dist: sphinx>=6.1; extra == 'doc'
Provides-Extra: test
Requires-Dist: pytest; extra == 'test'
